{
  "sections": {
    "custom_annoucement_bar_MHC9F4": {
      "type": "custom-annoucement-bar",
      "settings": {
        "background_color": "#f43636",
        "text_color": "#000000",
        "auto_rotate": true,
        "rotation_interval": 3
      }
    },
    "main": {
      "type": "main-product",
      "blocks": {
        "vendor": {
          "type": "text",
          "settings": {
            "text": "{{ product.vendor }}",
            "text_style": "uppercase"
          }
        },
        "title": {
          "type": "title",
          "settings": {
          }
        },
        "price": {
          "type": "price",
          "settings": {
          }
        },
        "variant_picker": {
          "type": "variant_picker",
          "settings": {
            "picker_type": "button",
            "swatch_shape": "circle"
          }
        },
        "quantity_selector": {
          "type": "quantity_selector",
          "settings": {
          }
        },
        "free_shipping_block_i9V8RP": {
          "type": "free_shipping_block",
          "settings": {
            "free_shipping_icon": "shopify:\/\/shop_images\/delivery-truck.png",
            "free_shipping_text": "This product has free shipping",
            "price_threshold": 100
          }
        },
        "fragile_product_tag_7zJtKc": {
          "type": "fragile_product_tag",
          "settings": {
            "fragile_tag": "fragile",
            "fragile_msg": "This is a fragile product"
          }
        },
        "buy_buttons": {
          "type": "buy_buttons",
          "settings": {
            "show_dynamic_checkout": true,
            "show_gift_card_recipient": true
          }
        },
        "share": {
          "type": "share",
          "settings": {
            "share_label": "Share"
          }
        }
      },
      "block_order": [
        "vendor",
        "title",
        "price",
        "variant_picker",
        "quantity_selector",
        "free_shipping_block_i9V8RP",
        "fragile_product_tag_7zJtKc",
        "buy_buttons",
        "share"
      ],
      "custom_css": [
        ".product__text {font-size: 18px; margin-bottom: 8px; font-weight: bold;}"
      ],
      "settings": {
        "enable_sticky_info": false,
        "color_scheme": "scheme-1",
        "media_size": "small",
        "constrain_to_viewport": true,
        "media_fit": "contain",
        "gallery_layout": "columns",
        "media_position": "left",
        "image_zoom": "lightbox",
        "mobile_thumbnails": "hide",
        "hide_variants": true,
        "enable_video_looping": false,
        "padding_top": 36,
        "padding_bottom": 12
      }
    },
    "image_with_text_cGcNLt": {
      "type": "image-with-text",
      "blocks": {
        "heading_PnVyFB": {
          "type": "heading",
          "settings": {
            "heading": "{{ product.metafields.custom.brand_metafield.value.brand_name.value }}",
            "heading_size": "h1"
          }
        },
        "text_djy4Bx": {
          "type": "text",
          "settings": {
            "text": "<p>{{ product.metafields.custom.brand_metafield.value.dsecription | metafield_tag }}<\/p>",
            "text_style": "body"
          }
        },
        "button_MaURFw": {
          "type": "button",
          "settings": {
            "button_label": "Shop Now",
            "button_link": "{{ product.metafields.custom.brand_metafield.value.brand_collection_url.value }}",
            "button_style_secondary": false
          }
        }
      },
      "block_order": [
        "heading_PnVyFB",
        "text_djy4Bx",
        "button_MaURFw"
      ],
      "settings": {
        "image": "{{ product.metafields.custom.brand_metafield.value.brand_image.value }}",
        "height": "adapt",
        "desktop_image_width": "medium",
        "layout": "image_first",
        "desktop_content_position": "top",
        "desktop_content_alignment": "left",
        "content_layout": "no-overlap",
        "section_color_scheme": "",
        "color_scheme": "",
        "image_behavior": "none",
        "mobile_content_alignment": "left",
        "padding_top": 36,
        "padding_bottom": 36
      }
    },
    "related-products": {
      "type": "related-products",
      "settings": {
        "heading": "You may also like",
        "heading_size": "h2",
        "products_to_show": 4,
        "columns_desktop": 4,
        "color_scheme": "scheme-1",
        "image_ratio": "square",
        "image_shape": "default",
        "show_secondary_image": true,
        "show_vendor": false,
        "show_rating": false,
        "columns_mobile": "2",
        "padding_top": 36,
        "padding_bottom": 28
      }
    }
  },
  "order": [
    "custom_annoucement_bar_MHC9F4",
    "main",
    "image_with_text_cGcNLt",
    "related-products"
  ]
}
